Workbook

Sheet Summary
A1: Lead Router: Test Protocol and Results
A2: Demo build by Solvant Labs for a B2B IT services scenario. Yellow cells are for you to fill in; everything else is calculated.
A4: Test run details
A5: Executed by | B5: Olaoluwa Ilesanmi (browser steps run with Claude in Chrome)
A6: Date | B6: 2026-10-05
A7: Environment | B7: n8n Cloud; Neon Postgres; HubSpot free CRM; Slack; Google Sheets API; Gmail SMTP
A8: Test Runner run ID | B8: tvo47hy (99 Test Runner execution 110)
A9: Workflow versions tested | B9: 02 version 1fb42d20; 01 version 97fcd65b (sheet poller off); 03 as published on 5 Oct 2026
A11: Results
B12: Total | C12: Passed | D12: Failed | E12: Not run yet
A13: Automated | B13: =COUNTA(Automated!A6:A27) | C13: =COUNTIF(Automated!G6:G27,"PASS") | D13: =COUNTIF(Automated!G6:G27,"FAIL") | E13: =B13-C13-D13
A14: Manual | B14: =COUNTA(Manual!A6:A16) | C14: =COUNTIF(Manual!G6:G16,"PASS") | D14: =COUNTIF(Manual!G6:G16,"FAIL") | E14: =B14-C14-D14
A15: Total | B15: =SUM(B13:B14) | C15: =SUM(C13:C14) | D15: =SUM(D13:D14) | E15: =SUM(E13:E14)
A17: Overall status | B17: =IF(D15>0,"FAILURES TO FIX",IF(E15>0,"IN PROGRESS","ALL PASSED"))
A18: Acceptance criteria met | B18: =COUNTIF(Traceability!M5:M13,"Met")&" of "&COUNTA(Traceability!A5:A13)
A20: How to use this workbook
A21: 1. Run workflow 99 - Test Runner with every rep available, then copy each result into the Automated tab.
A22: 2. Work through the Manual tab in order; M-03 to M-07 change settings, so put each one back afterwards.
A23: 3. Save each screenshot under its Evidence file name; they are also your portfolio images.
A24: 4. When Overall status shows ALL PASSED, fill in the run details above and keep a PDF copy with the repo.

Sheet Automated
A1: Automated tests (workflow 99 - Test Runner)
A2: Fill in the yellow columns after a run. Copy each Actual result from the view v_latest_test_run in Adminer (or the Evaluate Results node in n8n), then set Pass/Fail to PASS or FAIL. Row 5 is an example; leave it as is.
A4: Test ID | B4: Scenario | C4: Input | D4: Expected result | E4: Acceptance criteria | F4: Actual result | G4: Pass/Fail | H4: Notes
A5: EXAMPLE | B5: Clean lead in an East state is routed by territory | C5: Massachusetts dental group | D5: routed; Cold; score 35; pool east | E5: AC-01 | F5: event=routed, priority=Cold, score=35, pool=east, route_type=territory | G5: PASS | H5: Run t1abcd, 6 Oct 2026
A6: TC-01 | B6: Clean lead in an East state is routed by territory | C6: Massachusetts dental group, 35 staff, $8,000, Managed IT, 1-3 months | D6: routed; Cold; score 35; pool east; route territory; email lowercased; phone +16175550101; state MA; size 11-50; budget $5k-$15k | E6: AC-01 | F6: event: routed, priority: Cold, score: 35, pool: east, route_type: territory, email: ava.martin+tvo47hy@harborviewdental.example.com, phone: +16175550101, state: MA, country: US, company_size_band: 11-50, budget_band: $5k-$15k | G6: PASS | H6: Run tvo47hy, 5 Oct 2026
A7: TC-02 | B7: Lead in a West state goes to the West pool | C7: Oregon brewery, 11-50 staff, $15k-$50k, Cybersecurity, 3-6 months | D7: routed; Warm; score 50; pool west; route territory | E7: AC-01 | F7: event: routed, priority: Warm, score: 50, pool: west, route_type: territory, phone: +15035550102, state: OR, budget_band: $15k-$50k | G7: PASS | H7: Run tvo47hy, 5 Oct 2026
A8: TC-03 | B8: Hot lead goes to Enterprise regardless of territory | C8: Illinois health group, 450 staff, $75,000, Cloud Migration, ASAP, VP | D8: routed; Hot; score 105; pool enterprise; route score; size 201-1000; budget $50k+ | E8: AC-01 | F8: event: routed, priority: Hot, score: 105, pool: enterprise, route_type: score, company_size_band: 201-1000, budget_band: $50k+, phone: +13125550103 | G8: PASS | H8: Run tvo47hy, 5 Oct 2026
A9: TC-04 | B9: Messy input is cleaned | C9: Spaces, lowercase names, 'new york', 'u.s.', phone with extension, '8' staff, 'under 5k', 'managed it', 'asap' | D9: routed; names Liam / O'Connor; email lowercased and trimmed; phone +12125550104; state NY; country US; size 1-10; budget Under $5k; service Managed IT Support; timeline ASAP | E9: AC-01 | F9: event: routed, priority: Cold, score: 30, pool: east, first_name: Liam, last_name: O'Connor, email: liam.oconnor+tvo47hy@brightline.example.com, phone: +12125550104, state: NY, country: US, company_size_band: 1-10, budget_band: Under $5k, service_interest: Managed IT Support, timeline: ASAP | G9: PASS | H9: Run tvo47hy, 5 Oct 2026
A10: TC-05 | B10: Free email domain gets no business-email points | C10: Gmail address, owner of a 5-person firm, $5k-$15k, Microsoft 365 | D10: routed; Cold; score 35; email_type free | E10: AC-01 | F10: event: routed, priority: Cold, score: 35, pool: east, email_type: free, service_interest: Microsoft 365 Setup | G10: PASS | H10: Run tvo47hy, 5 Oct 2026
A11: TC-06 | B11: Lead outside the US goes to the Sales Manager | C11: French company, no state, 51-200 staff, Director | D11: routed; Warm; score 60; pool manager; route no_territory; rep Rachel Kim; phone +33142685300 | E11: AC-01 | F11: event: routed, priority: Warm, score: 60, pool: manager, route_type: no_territory, rep_id: rep_rachel, phone: +33142685300, country: France | G11: PASS | H11: Run tvo47hy, 5 Oct 2026
A12: TC-07 | B12: Second Hot lead rotates to the other Enterprise rep | C12: Georgia logistics, 1000+ staff, $50k+, CTO | D12: routed; Hot; score 115; pool enterprise; route score (balance across Enterprise reps is checked in TC-21) | E12: AC-04 | F12: event: routed, priority: Hot, score: 115, pool: enterprise, route_type: score | G12: PASS | H12: Run tvo47hy, 5 Oct 2026
A13: TC-08 | B13: East lead for round-robin balance | C13: New Jersey CPA firm, 11-50 staff | D13: routed; Cold; score 35; pool east | E13: AC-04 | F13: event: routed, priority: Cold, score: 35, pool: east, route_type: territory | G13: PASS | H13: Run tvo47hy, 5 Oct 2026
A14: TC-09 | B14: Budget range uses its midpoint | C14: Budget '10000-20000' | D14: routed; Warm; score 55; pool east; budget $15k-$50k | E14: AC-04 | F14: event: routed, priority: Warm, score: 55, pool: east, route_type: territory, budget_band: $15k-$50k | G14: PASS | H14: Run tvo47hy, 5 Oct 2026
A15: TC-10 | B15: West lead for round-robin balance | C15: Arizona clinic, Cybersecurity, ASAP | D15: routed; Warm; score 55; pool west | E15: AC-04 | F15: event: routed, priority: Warm, score: 55, pool: west, route_type: territory | G15: PASS | H15: Run tvo47hy, 5 Oct 2026
... A27: TC-22 | B27: Webhook acknowledges every valid delivery with 202 | C27: All 22 valid requests in the run | D27: 22 of 22 requests return 202 Accepted | E27: AC-06 | F27: 22 of 22 returned 202 | G27: PASS | H27: Run tvo47hy, 5 Oct 2026

Sheet Manual
A1: Manual tests
A2: Run each test, then fill in the yellow columns. Save a screenshot for each one under the Evidence file name (they double as portfolio images). Row 5 is an example; leave it as is.
A4: Test ID | B4: Scenario | C4: Steps | D4: Expected result | E4: Acceptance criteria | F4: Actual result | G4: Pass/Fail | H4: Evidence file | I4: Tested by | J4: Date
A5: EXAMPLE | B5: Web form submission end to end | C5: Submitted a Hot lead through the form | D5: #leads message within 60 seconds | E5: AC-01, AC-06 | F5: Slack message after 4 seconds, contact created, email received | G5: PASS | H5: M-01-slack.png | I5: O. Ilesanmi | J5: 2026-10-06
A6: M-01 | B6: Web form submission end to end | C6: Open http://localhost:5678/form/contact-sales in a browser. Submit a Hot lead with an email you have not used before (for example m01.yourname@formtest.example.com): 201-1000 employees, $50k+, Cybersecurity, ASAP, job title CTO. | D6: Thank-you message shows. Within 60 seconds: #leads message assigning an Enterprise rep, HubSpot contact with the Lead Router properties filled in, hot-lead email in that rep's inbox, lead_log row with event routed and source form. | E6: AC-01, AC-06 | F6: Hot lead submitted in the form (Sherry Clarke, CTO, 201-1000, $50k+, Cybersecurity, ASAP). Within 7 seconds: score 105, Hot, Enterprise pool, assigned to Sarah Whitfield; #leads message posted; HubSpot contact 564682615518 created with the Lead Router group; hot-lead email sent to Sarah's inbox; routed row with source form. | G6: PASS | H6: n8n 02 execution 197; Neon lead_log | I6: O. Ilesanmi | J6: 2026-10-05
A7: M-02 | B7: Google Sheet intake | C7: Copy the 3 rows from the sample_rows tab into the intake tab, leaving status blank. If you have pasted these rows before, change added_at on each one first. Wait up to 3 minutes. | D7: Grace Holloway: routed to an East rep (Warm, score 65). Tom Brennan: routed to a West rep (Warm, score 45). Lena Fischer: rejected, 'Missing email', plus a review alert in #lead-alerts. status, routed_to and processed_at are filled in on every row. | E7: AC-03, AC-06 | F7: One poll picked up the 3 rows. Grace Holloway routed East to Maya Chen (Warm, 65); Tom Brennan routed West to Priya Raman (Warm, 45); Lena Fischer rejected (Missing email) with a review alert. status, routed_to and processed_at filled on every row. | G7: PASS | H7: n8n 02 executions 193-195; intake tab | I7: O. Ilesanmi (browser steps via Claude in Chrome) | J7: 2026-10-05
A8: M-03 | B8: A rep marked unavailable is skipped | C8: In the reps tab set Maya Chen's available to FALSE. Run the 'Send one test lead' command twice with TEST=m03. Afterwards set Maya back to TRUE. | D8: Both leads go to Daniel Okafor. | E8: AC-05, AC-08 | F8: Maya Chen set to FALSE: both m03 leads went to Daniel Okafor. Maya set back to TRUE. | G8: PASS | H8: n8n 02 executions 157, 159; Neon lead_log | I8: O. Ilesanmi (browser steps via Claude in Chrome) | J8: 2026-10-05
A9: M-04 | B9: A pool with nobody available falls back to the manager | C9: Set Maya Chen and Daniel Okafor to FALSE. Run the 'Send one test lead' command with TEST=m04. Afterwards set both back to TRUE. | D9: Routed to Rachel Kim; routing reason mentions 'no available reps in the east pool'. | E9: AC-05 | F9: Maya Chen and Daniel Okafor set to FALSE: routed to Rachel Kim (manager pool, fallback); reason ends '(no available reps in the east pool)'. Both set back to TRUE. | G9: PASS | H9: n8n 02 execution 162; Neon lead_log | I9: O. Ilesanmi (browser steps via Claude in Chrome) | J9: 2026-10-05
A10: M-05 | B10: Scoring change takes effect without editing n8n | C10: In scoring_rules set R07 (ASAP) points to 40. Run the 'M-05 scoring lead' command (Oregon, 11-50 staff, $25,000, Cybersecurity, ASAP, business email, no job title). Afterwards set R07 back to 15. | D10: Score 90 instead of 65; priority Hot; routed to the Enterprise pool; Slack shows 'Buying now +40'. | E10: AC-08 | F10: R07 set to 40: score 90, Hot, Enterprise pool (James Adeyemi); breakdown shows Buying now +40. R07 set back to 15. | G10: PASS | H10: n8n 02 execution 165; Neon lead_log | I10: O. Ilesanmi (browser steps via Claude in Chrome) | J10: 2026-10-05
A11: M-06 | B11: CRM failure raises an alert and recovers cleanly | C11: Edit the 'Lead Router - HubSpot' credential and change one character of the key. Run the 'Send one test lead' command with TEST=m06. After the alert arrives, restore the key, open the failed execution from the alert link and click Retry. | D11: Within 1 minute: alert in #lead-alerts and by email naming the failed HubSpot step, with a link to the execution. After Retry: execution succeeds, exactly 1 HubSpot contact, 1 #leads message, 1 routed row in lead_log. | E11: AC-07, AC-01, AC-02 | F11: HubSpot key broken: 02 failed at Find Contact in HubSpot (Authorization failed). The error handler alerted 6 seconds later in #lead-alerts and by email, naming the step with a link to the run. Key restored by pasting it from HubSpot (a first retry failed because editing n8n's masked key field does not restore it). Retry then left 1 routed row, 1 new contact and 1 #leads message. | G11: PASS | H11: n8n 02 executions 203 (failure), 207 (retry); 03 execution 204 (alert) | I11: O. Ilesanmi (key) with Claude in Chrome (send and retry) | J11: 2026-10-05
A12: M-07 | B12: Alerts still arrive when Slack is down | C12: Edit the 'Lead Router - Slack' credential and break the token. Run the 'Send one test lead' command with TEST=m07. Then restore the token and retry the failed execution. | D12: Notify in Slack fails after 3 attempts; the failure email still arrives; after Retry the #leads message posts once. | E12: AC-07 | F12: Not run (skipped on 5 Oct 2026). | H12: M-07-email.png
A13: M-08 | B13: HubSpot record is complete and a partial resubmission loses nothing | C13: Open the M-01 contact in HubSpot. Then run the 'M-08 partial resubmission' command with the email, first name and company you used in M-01. | D13: Lead Router group shows score, priority, assigned rep, routing reason and source. After the resubmission the phone and job title are unchanged and the contact keeps the same rep (returning contact). | E13: AC-01 | F13: The M-01 contact's Lead Router group shows score, priority, assigned rep, routing reason and source. The partial m08 resubmission updated the same contact (not new), kept with Sarah Whitfield as a returning contact; job title still CTO, phone unchanged. | G13: PASS | H13: n8n 02 execution 200; HubSpot contact 564682615518 | I13: O. Ilesanmi (browser steps via Claude in Chrome) | J13: 2026-10-05
A14: M-09 | B14: Audit trail links every lead to its execution | C14: In Adminer open the view v_lead_activity. Copy the execution_id of any row. In n8n open 02 - Process Lead > Executions and find that ID. | D14: Every test event has one row; the execution opens and shows the lead's path through the workflow. | E14: AC-03, AC-07 | F14: lead_log has 66 final rows for 66 distinct events, none without an execution_id. The m05 row's execution 165 shows that lead's full path. | G14: PASS | H14: Neon query on lead_log; n8n 02 execution 165 | I14: O. Ilesanmi (browser steps via Claude in Chrome) | J14: 2026-10-05
A15: M-10 | B15: Webhook without an API key is refused | C15: Run the 'M-10 no API key' command. | D15: HTTP 403; no lead_log row for that event. | E15: AC-09 | F15: HTTP 403 without the API key; 0 lead_log rows for that event. | G15: PASS | H15: n8n 98 execution 166; Neon query | I15: O. Ilesanmi (browser steps via Claude in Chrome) | J15: 2026-10-05
A16: M-11 | B16: A burst of simultaneous leads stays balanced | C16: Run the command in the setup guide's 'Load check' section, which sends 12 New York leads at the same instant and prints a run number. Then run the SQL query shown there in Adminer with that run number. | D16: All 12 routed; split 6 and 6 between Maya Chen and Daniel Okafor; no failed executions. | E16: AC-04 | F16: Run 200622: 12 simultaneous New York leads, all HTTP 202, all routed, 6 to Maya Chen and 6 to Daniel Okafor, no failed executions. | G16: PASS | H16: n8n 98 execution 167; Neon query | I16: O. Ilesanmi (browser steps via Claude in Chrome) | J16: 2026-10-05

Sheet Traceability
A1: Acceptance criteria traceability
A2: Each criterion from the project brief, the tests that prove it, and their results. Everything on this sheet is calculated; nothing to fill in.
A4: Criterion | B4: Description | C4: Test 1 | D4: Test 2 | E4: Test 3 | F4: Test 4 | G4: Test 5 | H4: Result 1 | I4: Result 2 | J4: Result 3 | K4: Result 4 | L4: Result 5 | M4: Status
A5: AC-01 | B5: Each valid lead creates or updates exactly one HubSpot contact | C5: TC-01 | D5: TC-16 | E5: M-01 | F5: M-06 | G5: M-08 | H5: =IF(C5="","",IFERROR(INDEX(Automated!$G$6:$G$27,MATCH(C5,Automated!$A$6:$A$27,0))&"",IFERROR(INDEX(Manual!$G$6:$G$16,MATCH(C5,Manual!$A$6:$A$16,0))&"","?"))) | I5: =IF(D5="","",IFERROR(INDEX(Automated!$G$6:$G$27,MATCH(D5,Automated!$A$6:$A$27,0))&"",IFERROR(INDEX(Manual!$G$6:$G$16,MATCH(D5,Manual!$A$6:$A$16,0))&"","?"))) | J5: =IF(E5="","",IFERROR(INDEX(Automated!$G$6:$G$27,MATCH(E5,Automated!$A$6:$A$27,0))&"",IFERROR(INDEX(Manual!$G$6:$G$16,MATCH(E5,Manual!$A$6:$A$16,0))&"","?"))) | K5: =IF(F5="","",IFERROR(INDEX(Automated!$G$6:$G$27,MATCH(F5,Automated!$A$6:$A$27,0))&"",IFERROR(INDEX(Manual!$G$6:$G$16,MATCH(F5,Manual!$A$6:$A$16,0))&"","?"))) | L5: =IF(G5="","",IFERROR(INDEX(Automated!$G$6:$G$27,MATCH(G5,Automated!$A$6:$A$27,0))&"",IFERROR(INDEX(Manual!$G$6:$G$16,MATCH(G5,Manual!$A$6:$A$16,0))&"","?"))) | M5: =IF(COUNTIF(H5:L5,"FAIL")>0,"Not met",IF(COUNTIF(H5:L5,"PASS")=COUNTA(C5:G5),"Met","Pending"))
A6: AC-02 | B6: A repeated delivery creates no extra contacts, Slack messages or emails | C6: TC-14 | D6: TC-15 | E6: TC-16 | F6: M-06 | H6: =IF(C6="","",IFERROR(INDEX(Automated!$G$6:$G$27,MATCH(C6,Automated!$A$6:$A$27,0))&"",IFERROR(INDEX(Manual!$G$6:$G$16,MATCH(C6,Manual!$A$6:$A$16,0))&"","?"))) | I6: =IF(D6="","",IFERROR(INDEX(Automated!$G$6:$G$27,MATCH(D6,Automated!$A$6:$A$27,0))&"",IFERROR(INDEX(Manual!$G$6:$G$16,MATCH(D6,Manual!$A$6:$A$16,0))&"","?"))) | J6: =IF(E6="","",IFERROR(INDEX(Automated!$G$6:$G$27,MATCH(E6,Automated!$A$6:$A$27,0))&"",IFERROR(INDEX(Manual!$G$6:$G$16,MATCH(E6,Manual!$A$6:$A$16,0))&"","?"))) | K6: =IF(F6="","",IFERROR(INDEX(Automated!$G$6:$G$27,MATCH(F6,Automated!$A$6:$A$27,0))&"",IFERROR(INDEX(Manual!$G$6:$G$16,MATCH(F6,Manual!$A$6:$A$16,0))&"","?"))) | L6: =IF(G6="","",IFERROR(INDEX(Automated!$G$6:$G$27,MATCH(G6,Automated!$A$6:$A$27,0))&"",IFERROR(INDEX(Manual!$G$6:$G$16,MATCH(G6,Manual!$A$6:$A$16,0))&"","?"))) | M6: =IF(COUNTIF(H6:L6,"FAIL")>0,"Not met",IF(COUNTIF(H6:L6,"PASS")=COUNTA(C6:G6),"Met","Pending"))
A7: AC-03 | B7: Each invalid lead produces one log row and one review alert, never a silent drop | C7: TC-11 | D7: TC-12 | E7: TC-13 | F7: TC-20 | G7: M-02 | H7: =IF(C7="","",IFERROR(INDEX(Automated!$G$6:$G$27,MATCH(C7,Automated!$A$6:$A$27,0))&"",IFERROR(INDEX(Manual!$G$6:$G$16,MATCH(C7,Manual!$A$6:$A$16,0))&"","?"))) | I7: =IF(D7="","",IFERROR(INDEX(Automated!$G$6:$G$27,MATCH(D7,Automated!$A$6:$A$27,0))&"",IFERROR(INDEX(Manual!$G$6:$G$16,MATCH(D7,Manual!$A$6:$A$16,0))&"","?"))) | J7: =IF(E7="","",IFERROR(INDEX(Automated!$G$6:$G$27,MATCH(E7,Automated!$A$6:$A$27,0))&"",IFERROR(INDEX(Manual!$G$6:$G$16,MATCH(E7,Manual!$A$6:$A$16,0))&"","?"))) | K7: =IF(F7="","",IFERROR(INDEX(Automated!$G$6:$G$27,MATCH(F7,Automated!$A$6:$A$27,0))&"",IFERROR(INDEX(Manual!$G$6:$G$16,MATCH(F7,Manual!$A$6:$A$16,0))&"","?"))) | L7: =IF(G7="","",IFERROR(INDEX(Automated!$G$6:$G$27,MATCH(G7,Automated!$A$6:$A$27,0))&"",IFERROR(INDEX(Manual!$G$6:$G$16,MATCH(G7,Manual!$A$6:$A$16,0))&"","?"))) | M7: =IF(COUNTIF(H7:L7,"FAIL")>0,"Not met",IF(COUNTIF(H7:L7,"PASS")=COUNTA(C7:G7),"Met","Pending"))
A8: AC-04 | B8: Available reps in a pool receive leads evenly (difference of 1 at most) | C8: TC-07 | D8: TC-21 | E8: M-11 | H8: =IF(C8="","",IFERROR(INDEX(Automated!$G$6:$G$27,MATCH(C8,Automated!$A$6:$A$27,0))&"",IFERROR(INDEX(Manual!$G$6:$G$16,MATCH(C8,Manual!$A$6:$A$16,0))&"","?"))) | I8: =IF(D8="","",IFERROR(INDEX(Automated!$G$6:$G$27,MATCH(D8,Automated!$A$6:$A$27,0))&"",IFERROR(INDEX(Manual!$G$6:$G$16,MATCH(D8,Manual!$A$6:$A$16,0))&"","?"))) | J8: =IF(E8="","",IFERROR(INDEX(Automated!$G$6:$G$27,MATCH(E8,Automated!$A$6:$A$27,0))&"",IFERROR(INDEX(Manual!$G$6:$G$16,MATCH(E8,Manual!$A$6:$A$16,0))&"","?"))) | K8: =IF(F8="","",IFERROR(INDEX(Automated!$G$6:$G$27,MATCH(F8,Automated!$A$6:$A$27,0))&"",IFERROR(INDEX(Manual!$G$6:$G$16,MATCH(F8,Manual!$A$6:$A$16,0))&"","?"))) | L8: =IF(G8="","",IFERROR(INDEX(Automated!$G$6:$G$27,MATCH(G8,Automated!$A$6:$A$27,0))&"",IFERROR(INDEX(Manual!$G$6:$G$16,MATCH(G8,Manual!$A$6:$A$16,0))&"","?"))) | M8: =IF(COUNTIF(H8:L8,"FAIL")>0,"Not met",IF(COUNTIF(H8:L8,"PASS")=COUNTA(C8:G8),"Met","Pending"))
A9: AC-05 | B9: A rep marked unavailable receives no new leads | C9: M-03 | D9: M-04 | H9: =IF(C9="","",IFERROR(INDEX(Automated!$G$6:$G$27,MATCH(C9,Automated!$A$6:$A$27,0))&"",IFERROR(INDEX(Manual!$G$6:$G$16,MATCH(C9,Manual!$A$6:$A$16,0))&"","?"))) | I9: =IF(D9="","",IFERROR(INDEX(Automated!$G$6:$G$27,MATCH(D9,Automated!$A$6:$A$27,0))&"",IFERROR(INDEX(Manual!$G$6:$G$16,MATCH(D9,Manual!$A$6:$A$16,0))&"","?"))) | J9: =IF(E9="","",IFERROR(INDEX(Automated!$G$6:$G$27,MATCH(E9,Automated!$A$6:$A$27,0))&"",IFERROR(INDEX(Manual!$G$6:$G$16,MATCH(E9,Manual!$A$6:$A$16,0))&"","?"))) | K9: =IF(F9="","",IFERROR(INDEX(Automated!$G$6:$G$27,MATCH(F9,Automated!$A$6:$A$27,0))&"",IFERROR(INDEX(Manual!$G$6:$G$16,MATCH(F9,Manual!$A$6:$A$16,0))&"","?"))) | L9: =IF(G9="","",IFERROR(INDEX(Automated!$G$6:$G$27,MATCH(G9,Automated!$A$6:$A$27,0))&"",IFERROR(INDEX(Manual!$G$6:$G$16,MATCH(G9,Manual!$A$6:$A$16,0))&"","?"))) | M9: =IF(COUNTIF(H9:L9,"FAIL")>0,"Not met",IF(COUNTIF(H9:L9,"PASS")=COUNTA(C9:G9),"Met","Pending"))
A10: AC-06 | B10: The rep is notified within 60 s (form, webhook) or 3 min (sheet) | C10: TC-22 | D10: M-01 | E10: M-02 | H10: =IF(C10="","",IFERROR(INDEX(Automated!$G$6:$G$27,MATCH(C10,Automated!$A$6:$A$27,0))&"",IFERROR(INDEX(Manual!$G$6:$G$16,MATCH(C10,Manual!$A$6:$A$16,0))&"","?"))) | I10: =IF(D10="","",IFERROR(INDEX(Automated!$G$6:$G$27,MATCH(D10,Automated!$A$6:$A$27,0))&"",IFERROR(INDEX(Manual!$G$6:$G$16,MATCH(D10,Manual!$A$6:$A$16,0))&"","?"))) | J10: =IF(E10="","",IFERROR(INDEX(Automated!$G$6:$G$27,MATCH(E10,Automated!$A$6:$A$27,0))&"",IFERROR(INDEX(Manual!$G$6:$G$16,MATCH(E10,Manual!$A$6:$A$16,0))&"","?"))) | K10: =IF(F10="","",IFERROR(INDEX(Automated!$G$6:$G$27,MATCH(F10,Automated!$A$6:$A$27,0))&"",IFERROR(INDEX(Manual!$G$6:$G$16,MATCH(F10,Manual!$A$6:$A$16,0))&"","?"))) | L10: =IF(G10="","",IFERROR(INDEX(Automated!$G$6:$G$27,MATCH(G10,Automated!$A$6:$A$27,0))&"",IFERROR(INDEX(Manual!$G$6:$G$16,MATCH(G10,Manual!$A$6:$A$16,0))&"","?"))) | M10: =IF(COUNTIF(H10:L10,"FAIL")>0,"Not met",IF(COUNTIF(H10:L10,"PASS")=COUNTA(C10:G10),"Met","Pending"))
A11: AC-07 | B11: A failed run raises an alert within 1 minute with a link to the execution | C11: M-06 | D11: M-07 | E11: M-09 | H11: =IF(C11="","",IFERROR(INDEX(Automated!$G$6:$G$27,MATCH(C11,Automated!$A$6:$A$27,0))&"",IFERROR(INDEX(Manual!$G$6:$G$16,MATCH(C11,Manual!$A$6:$A$16,0))&"","?"))) | I11: =IF(D11="","",IFERROR(INDEX(Automated!$G$6:$G$27,MATCH(D11,Automated!$A$6:$A$27,0))&"",IFERROR(INDEX(Manual!$G$6:$G$16,MATCH(D11,Manual!$A$6:$A$16,0))&"","?"))) | J11: =IF(E11="","",IFERROR(INDEX(Automated!$G$6:$G$27,MATCH(E11,Automated!$A$6:$A$27,0))&"",IFERROR(INDEX(Manual!$G$6:$G$16,MATCH(E11,Manual!$A$6:$A$16,0))&"","?"))) | K11: =IF(F11="","",IFERROR(INDEX(Automated!$G$6:$G$27,MATCH(F11,Automated!$A$6:$A$27,0))&"",IFERROR(INDEX(Manual!$G$6:$G$16,MATCH(F11,Manual!$A$6:$A$16,0))&"","?"))) | L11: =IF(G11="","",IFERROR(INDEX(Automated!$G$6:$G$27,MATCH(G11,Automated!$A$6:$A$27,0))&"",IFERROR(INDEX(Manual!$G$6:$G$16,MATCH(G11,Manual!$A$6:$A$16,0))&"","?"))) | M11: =IF(COUNTIF(H11:L11,"FAIL")>0,"Not met",IF(COUNTIF(H11:L11,"PASS")=COUNTA(C11:G11),"Met","Pending"))
A12: AC-08 | B12: Scoring points and rep availability change in the sheet without editing n8n | C12: M-03 | D12: M-05 | H12: =IF(C12="","",IFERROR(INDEX(Automated!$G$6:$G$27,MATCH(C12,Automated!$A$6:$A$27,0))&"",IFERROR(INDEX(Manual!$G$6:$G$16,MATCH(C12,Manual!$A$6:$A$16,0))&"","?"))) | I12: =IF(D12="","",IFERROR(INDEX(Automated!$G$6:$G$27,MATCH(D12,Automated!$A$6:$A$27,0))&"",IFERROR(INDEX(Manual!$G$6:$G$16,MATCH(D12,Manual!$A$6:$A$16,0))&"","?"))) | J12: =IF(E12="","",IFERROR(INDEX(Automated!$G$6:$G$27,MATCH(E12,Automated!$A$6:$A$27,0))&"",IFERROR(INDEX(Manual!$G$6:$G$16,MATCH(E12,Manual!$A$6:$A$16,0))&"","?"))) | K12: =IF(F12="","",IFERROR(INDEX(Automated!$G$6:$G$27,MATCH(F12,Automated!$A$6:$A$27,0))&"",IFERROR(INDEX(Manual!$G$6:$G$16,MATCH(F12,Manual!$A$6:$A$16,0))&"","?"))) | L12: =IF(G12="","",IFERROR(INDEX(Automated!$G$6:$G$27,MATCH(G12,Automated!$A$6:$A$27,0))&"",IFERROR(INDEX(Manual!$G$6:$G$16,MATCH(G12,Manual!$A$6:$A$16,0))&"","?"))) | M12: =IF(COUNTIF(H12:L12,"FAIL")>0,"Not met",IF(COUNTIF(H12:L12,"PASS")=COUNTA(C12:G12),"Met","Pending"))
A13: AC-09 | B13: Webhook calls without the correct API key are rejected | C13: TC-17 | D13: M-10 | H13: =IF(C13="","",IFERROR(INDEX(Automated!$G$6:$G$27,MATCH(C13,Automated!$A$6:$A$27,0))&"",IFERROR(INDEX(Manual!$G$6:$G$16,MATCH(C13,Manual!$A$6:$A$16,0))&"","?"))) | I13: =IF(D13="","",IFERROR(INDEX(Automated!$G$6:$G$27,MATCH(D13,Automated!$A$6:$A$27,0))&"",IFERROR(INDEX(Manual!$G$6:$G$16,MATCH(D13,Manual!$A$6:$A$16,0))&"","?"))) | J13: =IF(E13="","",IFERROR(INDEX(Automated!$G$6:$G$27,MATCH(E13,Automated!$A$6:$A$27,0))&"",IFERROR(INDEX(Manual!$G$6:$G$16,MATCH(E13,Manual!$A$6:$A$16,0))&"","?"))) | K13: =IF(F13="","",IFERROR(INDEX(Automated!$G$6:$G$27,MATCH(F13,Automated!$A$6:$A$27,0))&"",IFERROR(INDEX(Manual!$G$6:$G$16,MATCH(F13,Manual!$A$6:$A$16,0))&"","?"))) | L13: =IF(G13="","",IFERROR(INDEX(Automated!$G$6:$G$27,MATCH(G13,Automated!$A$6:$A$27,0))&"",IFERROR(INDEX(Manual!$G$6:$G$16,MATCH(G13,Manual!$A$6:$A$16,0))&"","?"))) | M13: =IF(COUNTIF(H13:L13,"FAIL")>0,"Not met",IF(COUNTIF(H13:L13,"PASS")=COUNTA(C13:G13),"Met","Pending"))
